uniset/__init__.py
uniset/_category/__init__.py
uniset/_category/cc.py
uniset/_category/cf.py
uniset/_category/cs.py
uniset/_category/ll.py
uniset/_category/lm.py
uniset/_category/lo.py
uniset/_category/lt.py
uniset/_category/lu.py
uniset/_category/mc.py
uniset/_category/me.py
uniset/_category/mn.py
uniset/_category/nd.py
uniset/_category/nl.py
uniset/_category/no.py
uniset/_category/pc.py
uniset/_category/pd.py
uniset/_category/pe.py
uniset/_category/pf.py
uniset/_category/pi.py
uniset/_category/po.py
uniset/_category/ps.py
uniset/_category/sc.py
uniset/_category/sk.py
uniset/_category/sm.py
uniset/_category/so.py
uniset/_category/zl.py
uniset/_category/zp.py
uniset/_category/zs.py
uniset/py.typed
uniset-0.1.0.dist-info/LICENSE
uniset-0.1.0.dist-info/WHEEL
uniset-0.1.0.dist-info/METADATA
uniset-0.1.0.dist-info/RECORD
