Metadata-Version: 2.1
Name: uniset
Version: 0.1.0
Summary: Pre-generated sets of Unicode code points
Home-page: https://github.com/hukkinj1/uniset
License: MIT
Keywords: unicode
Author: Taneli Hukkinen
Author-email: hukkinj1@users.noreply.github.com
Requires-Python: >=3.7
Classifier: License :: OSI Approved :: MIT License
Classifier: Operating System :: MacOS
Classifier: Operating System :: Microsoft :: Windows
Classifier: Operating System :: POSIX :: Linux
Classifier: Programming Language :: Python :: 3
Classifier: Programming Language :: Python :: 3.7
Classifier: Programming Language :: Python :: 3.8
Classifier: Programming Language :: Python :: 3.9
Classifier: Topic :: Software Development :: Libraries :: Python Modules
Classifier: Typing :: Typed
Project-URL: Repository, https://github.com/hukkinj1/uniset
